beiboot/__init__.py
beiboot/api/__init__.py
beiboot/api/connect.py
beiboot/api/create.py
beiboot/api/create_shelf.py
beiboot/api/delete.py
beiboot/api/delete_shelf.py
beiboot/api/heartbeat.py
beiboot/api/list.py
beiboot/api/list_shelves.py
beiboot/api/read.py
beiboot/api/read_shelf.py
beiboot/api/utils.py
beiboot/configuration.py
beiboot/connection/__init__.py
beiboot/connection/abstract.py
beiboot/connection/dummy/__init__.py
beiboot/connection/factory.py
beiboot/connection/ghostunnel/__init__.py
beiboot/connection/ghostunnel/docker.py
beiboot/connection/ghostunnel/native.py
beiboot/connection/types.py
beiboot/connection/utils.py
beiboot/misc/__init__.py
beiboot/misc/comps/__init__.py
beiboot/misc/comps/configmap.py
beiboot/misc/comps/deployment.py
beiboot/misc/comps/namespace.py
beiboot/misc/comps/rbac.py
beiboot/misc/comps/webhook.py
beiboot/misc/install.py
beiboot/misc/uninstall.py
beiboot/misc/utils.py
beiboot/types.py
beiboot/utils.py
beiboot-1.4.3.dist-info/METADATA
beiboot-1.4.3.dist-info/WHEEL
beiboot-1.4.3.dist-info/entry_points.txt
beiboot-1.4.3.dist-info/RECORD
