Metadata-Version: 2.1
Name: beiboot
Version: 1.4.3
Summary: Getdeck Beiboot client project.
Home-page: https://getdeck.dev
Keywords: Kubernetes,Development,Cloud-native
Author: Michael Schilonka
Author-email: michael@blueshoe.de
Requires-Python: >=3.9,<4.0
Classifier: Development Status :: 3 - Alpha
Classifier: Intended Audience :: Developers
Classifier: Operating System :: MacOS
Classifier: Operating System :: POSIX :: Linux
Classifier: Programming Language :: Python :: 3
Classifier: Programming Language :: Python :: 3.9
Classifier: Programming Language :: Python :: 3.10
Classifier: Programming Language :: Python :: 3.11
Classifier: Topic :: Software Development :: Build Tools
Requires-Dist: chardet (>=5.1.0,<6.0.0)
Requires-Dist: docker (>=6.0.0,<7.0.0)
Requires-Dist: kubernetes (>=23.3.0,<24.0.0)
Project-URL: Documentation, https://getdeck.dev
Project-URL: Repository, https://github.com/Getdeck/beiboot
